twisted/plugins/vumi_http_retry_api.py
twisted/plugins/vumi_http_retry_maintainer.py
twisted/plugins/vumi_http_retry_sender.py
vumi_http_retry/__init__.py
vumi_http_retry/limiter.py
vumi_http_retry/retries.py
vumi_http_retry/service.py
vumi_http_retry/worker.py
vumi_http_retry/tests/__init__.py
vumi_http_retry/tests/redis.py
vumi_http_retry/tests/test_limiter.py
vumi_http_retry/tests/test_redis.py
vumi_http_retry/tests/test_retries.py
vumi_http_retry/tests/test_service.py
vumi_http_retry/tests/utils.py
vumi_http_retry/tests/tests/__init__.py
vumi_http_retry/tests/tests/test_utils.py
vumi_http_retry/workers/__init__.py
vumi_http_retry/workers/api/__init__.py
vumi_http_retry/workers/api/service.py
vumi_http_retry/workers/api/utils.py
vumi_http_retry/workers/api/validate.py
vumi_http_retry/workers/api/worker.py
vumi_http_retry/workers/api/tests/__init__.py
vumi_http_retry/workers/api/tests/test_utils.py
vumi_http_retry/workers/api/tests/test_validate.py
vumi_http_retry/workers/api/tests/test_worker.py
vumi_http_retry/workers/maintainer/__init__.py
vumi_http_retry/workers/maintainer/service.py
vumi_http_retry/workers/maintainer/worker.py
vumi_http_retry/workers/maintainer/tests/__init__.py
vumi_http_retry/workers/maintainer/tests/test_worker.py
vumi_http_retry/workers/sender/__init__.py
vumi_http_retry/workers/sender/service.py
vumi_http_retry/workers/sender/worker.py
vumi_http_retry/workers/sender/tests/__init__.py
vumi_http_retry/workers/sender/tests/test_worker.py
vumi_http_retry_api-0.1.4.dist-info/DESCRIPTION.rst
vumi_http_retry_api-0.1.4.dist-info/METADATA
vumi_http_retry_api-0.1.4.dist-info/RECORD
vumi_http_retry_api-0.1.4.dist-info/WHEEL
vumi_http_retry_api-0.1.4.dist-info/metadata.json
vumi_http_retry_api-0.1.4.dist-info/top_level.txt
