Metadata-Version: 2.0
Name: vumi-http-retry-api
Version: 0.1.4
Summary: API for retrying HTTP requests
Home-page: http://github.com/praekelt/vumi-http-retry-api
Author: Praekelt Foundation
Author-email: dev@praekeltfoundation.org
License: BSD
Platform: UNKNOWN
Classifier: Development Status :: 4 - Beta
Classifier: Intended Audience :: Developers
Classifier: License :: OSI Approved :: BSD License
Classifier: Operating System :: POSIX
Classifier: Programming Language :: Python
Classifier: Topic :: Software Development :: Libraries :: Python Modules
Classifier: Topic :: Internet :: WWW/HTTP
Requires-Dist: PyYAML
Requires-Dist: confmodel
Requires-Dist: jsonschema
Requires-Dist: klein
Requires-Dist: treq
Requires-Dist: txredis
